mw_component/__init__.py
mw_component/frontend/build/asset-manifest.json
mw_component/frontend/build/bootstrap.min.css
mw_component/frontend/build/index.html
mw_component/frontend/build/precache-manifest.93a491426f36075dfc0723a2c85fbfce.js
mw_component/frontend/build/service-worker.js
mw_component/frontend/build/static/css/2.cbe79ea7.chunk.css
mw_component/frontend/build/static/css/2.cbe79ea7.chunk.css.map
mw_component/frontend/build/static/js/2.c9410cca.chunk.js
mw_component/frontend/build/static/js/2.c9410cca.chunk.js.LICENSE.txt
mw_component/frontend/build/static/js/2.c9410cca.chunk.js.map
mw_component/frontend/build/static/js/main.4489c64b.chunk.js
mw_component/frontend/build/static/js/main.4489c64b.chunk.js.map
mw_component/frontend/build/static/js/runtime-main.44d30fc2.js
mw_component/frontend/build/static/js/runtime-main.44d30fc2.js.map
mw_component/frontend/build/static/media/monoton-all-400-normal.5938dafd.woff
mw_component/frontend/build/static/media/monoton-latin-400-normal.68bccc3c.woff2
mw_component-0.0.1.dist-info/LICENSE
mw_component-0.0.1.dist-info/METADATA
mw_component-0.0.1.dist-info/WHEEL
mw_component-0.0.1.dist-info/top_level.txt
mw_component-0.0.1.dist-info/RECORD
